ZhihuWendaXiangBaZijiDeShujiSaomiaoChengPdfShenmeyangDeSaomiaoyiBijiaoHeshiFix1/README.md
ZhihuWendaXiangBaZijiDeShujiSaomiaoChengPdfShenmeyangDeSaomiaoyiBijiaoHeshiFix1/__init__.py
ZhihuWendaXiangBaZijiDeShujiSaomiaoChengPdfShenmeyangDeSaomiaoyiBijiaoHeshiFix1/__main__.py
ZhihuWendaXiangBaZijiDeShujiSaomiaoChengPdfShenmeyangDeSaomiaoyiBijiaoHeshiFix1/file.epub
ZhihuWendaXiangBaZijiDeShujiSaomiaoChengPdfShenmeyangDeSaomiaoyiBijiaoHeshiFix1/index.html
ZhihuWendaXiangBaZijiDeShujiSaomiaoChengPdfShenmeyangDeSaomiaoyiBijiaoHeshiFix1/css/__init__.py
ZhihuWendaXiangBaZijiDeShujiSaomiaoChengPdfShenmeyangDeSaomiaoyiBijiaoHeshiFix1/css/annotations.css
ZhihuWendaXiangBaZijiDeShujiSaomiaoChengPdfShenmeyangDeSaomiaoyiBijiaoHeshiFix1/css/main.css
ZhihuWendaXiangBaZijiDeShujiSaomiaoChengPdfShenmeyangDeSaomiaoyiBijiaoHeshiFix1/css/normalize.css
ZhihuWendaXiangBaZijiDeShujiSaomiaoChengPdfShenmeyangDeSaomiaoyiBijiaoHeshiFix1/css/popup.css
ZhihuWendaXiangBaZijiDeShujiSaomiaoChengPdfShenmeyangDeSaomiaoyiBijiaoHeshiFix1/font/__init__.py
ZhihuWendaXiangBaZijiDeShujiSaomiaoChengPdfShenmeyangDeSaomiaoyiBijiaoHeshiFix1/font/fontello.eot
ZhihuWendaXiangBaZijiDeShujiSaomiaoChengPdfShenmeyangDeSaomiaoyiBijiaoHeshiFix1/font/fontello.svg
ZhihuWendaXiangBaZijiDeShujiSaomiaoChengPdfShenmeyangDeSaomiaoyiBijiaoHeshiFix1/font/fontello.ttf
ZhihuWendaXiangBaZijiDeShujiSaomiaoChengPdfShenmeyangDeSaomiaoyiBijiaoHeshiFix1/font/fontello.woff
ZhihuWendaXiangBaZijiDeShujiSaomiaoChengPdfShenmeyangDeSaomiaoyiBijiaoHeshiFix1/img/__init__.py
ZhihuWendaXiangBaZijiDeShujiSaomiaoChengPdfShenmeyangDeSaomiaoyiBijiaoHeshiFix1/img/annotator-glyph-sprite.png
ZhihuWendaXiangBaZijiDeShujiSaomiaoChengPdfShenmeyangDeSaomiaoyiBijiaoHeshiFix1/img/annotator-icon-sprite.png
ZhihuWendaXiangBaZijiDeShujiSaomiaoChengPdfShenmeyangDeSaomiaoyiBijiaoHeshiFix1/img/apple-touch-icon.png
ZhihuWendaXiangBaZijiDeShujiSaomiaoChengPdfShenmeyangDeSaomiaoyiBijiaoHeshiFix1/img/cancelfullscreen.png
zhihu_wenda_xiang_ba_ziji_de_shuji_saomiao_cheng_pdf_shenmeyang_de_saomiaoyi_bijiao_heshi_fix1-2025.3.24.1.dist-info/METADATA
zhihu_wenda_xiang_ba_ziji_de_shuji_saomiao_cheng_pdf_shenmeyang_de_saomiaoyi_bijiao_heshi_fix1-2025.3.24.1.dist-info/WHEEL
zhihu_wenda_xiang_ba_ziji_de_shuji_saomiao_cheng_pdf_shenmeyang_de_saomiaoyi_bijiao_heshi_fix1-2025.3.24.1.dist-info/entry_points.txt
zhihu_wenda_xiang_ba_ziji_de_shuji_saomiao_cheng_pdf_shenmeyang_de_saomiaoyi_bijiao_heshi_fix1-2025.3.24.1.dist-info/top_level.txt
zhihu_wenda_xiang_ba_ziji_de_shuji_saomiao_cheng_pdf_shenmeyang_de_saomiaoyi_bijiao_heshi_fix1-2025.3.24.1.dist-info/RECORD
